[
    {
        "type": "message",
        "text": "",
        "files": [
            {
                "id": "FJV6R2M7A",
                "created": 1558403805,
                "timestamp": 1558403805,
                "name": "received_1617840338360407.jpeg",
                "title": "received_1617840338360407.jpeg",
                "mimetype": "image\/jpeg",
                "filetype": "jpg",
                "pretty_type": "JPEG",
                "user": "U3QMCLQQG",
                "editable": false,
                "size": 25841,
                "mode": "hosted",
                "is_external": false,
                "external_type": "",
                "is_public": true,
                "public_url_shared": false,
                "display_as_bot": false,
                "username": "",
                "url_private": "https:\/\/files.slack.com\/files-pri\/T286HM2F3-FJV6R2M7A\/received_1617840338360407.jpeg?t=xoxe-76221716513-794073583234-794073583266-1ff3cf69954d6ebcea7887b8cddaed05",
                "url_private_download": "https:\/\/files.slack.com\/files-pri\/T286HM2F3-FJV6R2M7A\/download\/received_1617840338360407.jpeg?t=xoxe-76221716513-794073583234-794073583266-1ff3cf69954d6ebcea7887b8cddaed05",
                "thumb_64": "https:\/\/files.slack.com\/files-tmb\/T286HM2F3-FJV6R2M7A-52fae820a2\/received_1617840338360407_64.jpg?t=xoxe-76221716513-794073583234-794073583266-1ff3cf69954d6ebcea7887b8cddaed05",
                "thumb_80": "https:\/\/files.slack.com\/files-tmb\/T286HM2F3-FJV6R2M7A-52fae820a2\/received_1617840338360407_80.jpg?t=xoxe-76221716513-794073583234-794073583266-1ff3cf69954d6ebcea7887b8cddaed05",
                "thumb_360": "https:\/\/files.slack.com\/files-tmb\/T286HM2F3-FJV6R2M7A-52fae820a2\/received_1617840338360407_360.jpg?t=xoxe-76221716513-794073583234-794073583266-1ff3cf69954d6ebcea7887b8cddaed05",
                "thumb_360_w": 360,
                "thumb_360_h": 203,
                "thumb_480": "https:\/\/files.slack.com\/files-tmb\/T286HM2F3-FJV6R2M7A-52fae820a2\/received_1617840338360407_480.jpg?t=xoxe-76221716513-794073583234-794073583266-1ff3cf69954d6ebcea7887b8cddaed05",
                "thumb_480_w": 480,
                "thumb_480_h": 270,
                "thumb_160": "https:\/\/files.slack.com\/files-tmb\/T286HM2F3-FJV6R2M7A-52fae820a2\/received_1617840338360407_160.jpg?t=xoxe-76221716513-794073583234-794073583266-1ff3cf69954d6ebcea7887b8cddaed05",
                "thumb_720": "https:\/\/files.slack.com\/files-tmb\/T286HM2F3-FJV6R2M7A-52fae820a2\/received_1617840338360407_720.jpg?t=xoxe-76221716513-794073583234-794073583266-1ff3cf69954d6ebcea7887b8cddaed05",
                "thumb_720_w": 720,
                "thumb_720_h": 405,
                "image_exif_rotation": 1,
                "original_w": 768,
                "original_h": 432,
                "permalink": "https:\/\/edhrec.slack.com\/files\/U3QMCLQQG\/FJV6R2M7A\/received_1617840338360407.jpeg",
                "permalink_public": "https:\/\/slack-files.com\/T286HM2F3-FJV6R2M7A-1983ab3d7a",
                "is_starred": false,
                "has_rich_preview": false
            }
        ],
        "upload": true,
        "user": "U3QMCLQQG",
        "display_as_bot": false,
        "ts": "1558403806.013100",
        "client_msg_id": "6c53c355-928d-429c-a88b-84fa34d65829"
    },
    {
        "client_msg_id": "4d02ae3f-76e0-4fe0-a02a-a9a0e8183385",
        "type": "message",
        "text": "hahahaha",
        "user": "UFZFBJN30",
        "ts": "1558404406.013500",
        "team": "T286HM2F3",
        "user_team": "T286HM2F3",
        "source_team": "T286HM2F3",
        "user_profile": {
            "avatar_hash": "d62d55b17b89",
            "image_72": "https:\/\/avatars.slack-edge.com\/2019-02-04\/541997004147_d62d55b17b8952118342_72.jpg",
            "first_name": "Kyle",
            "real_name": "Kyle Keller",
            "display_name": "Kyle Keller",
            "team": "T286HM2F3",
            "name": "kelle458",
            "is_restricted": false,
            "is_ultra_restricted": false
        }
    }
]