[
    {
        "type": "message",
        "subtype": "bot_message",
        "text": "```2019-06-30 08:00:04,539 INFO New Trending 2019-06-30\n\n2019-06-30 08:00:04,546 INFO daily.py took 0:00:01.369935\n```",
        "ts": "1561881601.078000",
        "username": "edhrecbot",
        "icons": {
            "emoji": ":robot_face:",
            "image_64": "https:\/\/a.slack-edge.com\/37d58\/img\/emoji_2017_12_06\/apple\/1f916.png"
        },
        "bot_id": "B2867AJ5C"
    },
    {
        "type": "message",
        "subtype": "bot_message",
        "text": "```2019-06-30 08:18:15,917 INFO New Trending 2019-06-30\n{\"name\": \"Goblin War Party\", \"s\": [0, 1, 0, 2, 3, 6, 5], \"z\": 1.029617596926319}\n{\"name\": \"Teferi's Time Twist\", \"s\": [0, 3, 2, 4, 4, 8, 7], \"z\": 1.0021459912468829}\n{\"name\": \"Hushwing Gryff\", \"s\": [0, 1, 2, 4, 4, 5, 5], \"z\": 0.9910059291689344}\n{\"name\": \"Samut, Voice of Dissent\", \"s\": [0, 7, 5, 4, 6, 15, 12], \"z\": 0.9450859818438448}\n{\"name\": \"Dueling Grounds\", \"s\": [0, 1, 0, 3, 3, 4, 3], \"z\": 0.9366870743752483}\n{\"name\": \"Island Sanctuary\", \"s\": [0, 2, 1, 2, 3, 7, 4], \"z\": 0.9302648601850194}\n{\"name\": \"Ixidron\", \"s\": [0, 5, 2, 4, 5, 8, 6], \"z\": 0.9266853685891768}\n{\"name\": \"Sidar Kondo of Jamuraa\", \"s\": [0, 1, 1, 2, 2, 4, 3], \"z\": 0.9264853266258952}\n{\"name\": \"Koth of the Hammer\", \"s\": [0, 2, 3, 3, 3, 6, 7], \"z\": 0.9218271545987374}\n{\"name\": \"Tragic Arrogance\", \"s\": [0, 4, 3, 4, 3, 18, 16], \"z\": 0.9196689125023044}\n2019-06-30 08:18:15,936 INFO daily.py took 0:18:10.450277\n```",
        "ts": "1561882693.078100",
        "username": "edhrecbot",
        "icons": {
            "emoji": ":robot_face:",
            "image_64": "https:\/\/a.slack-edge.com\/37d58\/img\/emoji_2017_12_06\/apple\/1f916.png"
        },
        "bot_id": "B2867AJ5C"
    },
    {
        "type": "message",
        "subtype": "bot_message",
        "text": "```2019-06-30 20:08:14,321 WARNING Chaos Orb from Thopter Pie Network in <https:\/\/archidekt.com\/decks\/117993>\n```",
        "ts": "1561925290.078200",
        "username": "edhrecbot",
        "icons": {
            "emoji": ":robot_face:",
            "image_64": "https:\/\/a.slack-edge.com\/37d58\/img\/emoji_2017_12_06\/apple\/1f916.png"
        },
        "bot_id": "B2867AJ5C"
    },
    {
        "type": "message",
        "subtype": "bot_message",
        "text": "```2019-06-30 20:28:22,847 INFO archidekt.py took 0:24:27.309585\n```",
        "ts": "1561926499.078300",
        "username": "edhrecbot",
        "icons": {
            "emoji": ":robot_face:",
            "image_64": "https:\/\/a.slack-edge.com\/37d58\/img\/emoji_2017_12_06\/apple\/1f916.png"
        },
        "bot_id": "B2867AJ5C"
    },
    {
        "type": "message",
        "subtype": "bot_message",
        "text": "```2019-06-30 20:38:19,815 WARNING Chaos Orb from Blood Crypt FR in <https:\/\/deckstats.net\/decks\/51759\/1340932-queen-marchesa\/en>\n```",
        "ts": "1561927096.078400",
        "username": "edhrecbot",
        "icons": {
            "emoji": ":robot_face:",
            "image_64": "https:\/\/a.slack-edge.com\/37d58\/img\/emoji_2017_12_06\/apple\/1f916.png"
        },
        "bot_id": "B2867AJ5C"
    },
    {
        "type": "message",
        "subtype": "bot_message",
        "text": "```2019-06-30 20:39:56,340 WARNING Chaos Orb from Drakuseth, Maw of Flame in <https:\/\/deckstats.net\/decks\/132986\/1340856-kaalia-of-the-vast-2-0\/en>\n```",
        "ts": "1561927192.078500",
        "username": "edhrecbot",
        "icons": {
            "emoji": ":robot_face:",
            "image_64": "https:\/\/a.slack-edge.com\/37d58\/img\/emoji_2017_12_06\/apple\/1f916.png"
        },
        "bot_id": "B2867AJ5C"
    },
    {
        "type": "message",
        "subtype": "bot_message",
        "text": "```2019-06-30 20:56:06,372 INFO deckstats.py took 0:25:44.084390\n```",
        "ts": "1561928162.078600",
        "username": "edhrecbot",
        "icons": {
            "emoji": ":robot_face:",
            "image_64": "https:\/\/a.slack-edge.com\/37d58\/img\/emoji_2017_12_06\/apple\/1f916.png"
        },
        "bot_id": "B2867AJ5C"
    },
    {
        "type": "message",
        "subtype": "bot_message",
        "text": "```2019-06-30 21:33:46,743 WARNING Chaos Orb in <http:\/\/www.mtggoldfish.com\/deck\/2044201>\n```",
        "ts": "1561930423.078700",
        "username": "edhrecbot",
        "icons": {
            "emoji": ":robot_face:",
            "image_64": "https:\/\/a.slack-edge.com\/37d58\/img\/emoji_2017_12_06\/apple\/1f916.png"
        },
        "bot_id": "B2867AJ5C"
    },
    {
        "type": "message",
        "subtype": "bot_message",
        "text": "```2019-06-30 21:37:06,676 WARNING Chaos Orb in <http:\/\/www.mtggoldfish.com\/deck\/2044204>\n```",
        "ts": "1561930623.078800",
        "username": "edhrecbot",
        "icons": {
            "emoji": ":robot_face:",
            "image_64": "https:\/\/a.slack-edge.com\/37d58\/img\/emoji_2017_12_06\/apple\/1f916.png"
        },
        "bot_id": "B2867AJ5C"
    },
    {
        "type": "message",
        "subtype": "bot_message",
        "text": "```2019-06-30 21:38:40,945 WARNING Chaos Orb in <http:\/\/www.mtggoldfish.com\/deck\/2044202>\n```",
        "ts": "1561930717.078900",
        "username": "edhrecbot",
        "icons": {
            "emoji": ":robot_face:",
            "image_64": "https:\/\/a.slack-edge.com\/37d58\/img\/emoji_2017_12_06\/apple\/1f916.png"
        },
        "bot_id": "B2867AJ5C"
    },
    {
        "type": "message",
        "subtype": "bot_message",
        "text": "Nightly started, onlydecks=False, skipdecks=False",
        "ts": "1561930951.079000",
        "username": "edhrecbot",
        "icons": {
            "emoji": ":robot_face:",
            "image_64": "https:\/\/a.slack-edge.com\/37d58\/img\/emoji_2017_12_06\/apple\/1f916.png"
        },
        "bot_id": "B2867AJ5C"
    },
    {
        "type": "message",
        "subtype": "bot_message",
        "text": "```2019-06-30 21:45:55,201 INFO mtggoldfish.py took 0:29:31.057544\n```",
        "ts": "1561931151.079100",
        "username": "edhrecbot",
        "icons": {
            "emoji": ":robot_face:",
            "image_64": "https:\/\/a.slack-edge.com\/37d58\/img\/emoji_2017_12_06\/apple\/1f916.png"
        },
        "bot_id": "B2867AJ5C"
    },
    {
        "type": "message",
        "subtype": "bot_message",
        "text": "[BAD] We now have 2 dynamic.py running. Before we had 5.",
        "ts": "1561932304.079200",
        "username": "edhrecbot",
        "icons": {
            "emoji": ":robot_face:",
            "image_64": "https:\/\/a.slack-edge.com\/37d58\/img\/emoji_2017_12_06\/apple\/1f916.png"
        },
        "bot_id": "B2867AJ5C"
    },
    {
        "type": "message",
        "subtype": "bot_message",
        "text": "[BAD] \/usr\/share\/nginx\/html\/sets\/bfz.html has not been updated in the past 30 hours",
        "ts": "1561943103.079300",
        "username": "edhrecbot",
        "icons": {
            "emoji": ":robot_face:",
            "image_64": "https:\/\/a.slack-edge.com\/37d58\/img\/emoji_2017_12_06\/apple\/1f916.png"
        },
        "bot_id": "B2867AJ5C"
    },
    {
        "type": "message",
        "subtype": "bot_message",
        "text": "[BAD] \/usr\/share\/nginx\/html\/tribes\/allies.html has not been updated in the past 30 hours",
        "ts": "1561943104.079400",
        "username": "edhrecbot",
        "icons": {
            "emoji": ":robot_face:",
            "image_64": "https:\/\/a.slack-edge.com\/37d58\/img\/emoji_2017_12_06\/apple\/1f916.png"
        },
        "bot_id": "B2867AJ5C"
    },
    {
        "type": "message",
        "subtype": "bot_message",
        "text": "[BAD] \/usr\/share\/nginx\/html\/commanders\/wubrg.html has not been updated in the past 30 hours",
        "ts": "1561943104.079500",
        "username": "edhrecbot",
        "icons": {
            "emoji": ":robot_face:",
            "image_64": "https:\/\/a.slack-edge.com\/37d58\/img\/emoji_2017_12_06\/apple\/1f916.png"
        },
        "bot_id": "B2867AJ5C"
    },
    {
        "type": "message",
        "subtype": "bot_message",
        "text": "[BAD] \/usr\/share\/nginx\/html\/cards\/capsize.html has not been updated in the past 30 hours",
        "ts": "1561946703.079600",
        "username": "edhrecbot",
        "icons": {
            "emoji": ":robot_face:",
            "image_64": "https:\/\/a.slack-edge.com\/37d58\/img\/emoji_2017_12_06\/apple\/1f916.png"
        },
        "bot_id": "B2867AJ5C"
    },
    {
        "type": "message",
        "subtype": "bot_message",
        "text": "[BAD] \/usr\/share\/nginx\/html\/top\/g.html has not been updated in the past 30 hours",
        "ts": "1561946703.079700",
        "username": "edhrecbot",
        "icons": {
            "emoji": ":robot_face:",
            "image_64": "https:\/\/a.slack-edge.com\/37d58\/img\/emoji_2017_12_06\/apple\/1f916.png"
        },
        "bot_id": "B2867AJ5C"
    },
    {
        "type": "message",
        "subtype": "bot_message",
        "text": "[BAD] \/usr\/share\/nginx\/html\/commanders\/omnath-locus-of-mana.html has not been updated in the past 30 hours",
        "ts": "1561953904.079800",
        "username": "edhrecbot",
        "icons": {
            "emoji": ":robot_face:",
            "image_64": "https:\/\/a.slack-edge.com\/37d58\/img\/emoji_2017_12_06\/apple\/1f916.png"
        },
        "bot_id": "B2867AJ5C"
    },
    {
        "type": "message",
        "subtype": "bot_message",
        "text": "[BAD] \/usr\/share\/nginx\/html\/decks\/zedruu-the-greathearted.html has not been updated in the past 30 hours",
        "ts": "1561953904.079900",
        "username": "edhrecbot",
        "icons": {
            "emoji": ":robot_face:",
            "image_64": "https:\/\/a.slack-edge.com\/37d58\/img\/emoji_2017_12_06\/apple\/1f916.png"
        },
        "bot_id": "B2867AJ5C"
    }
]